[
  {
    "locaInfo": "type",
    "version": "number",
    "localVersion": "number",
    "userId": "string",
    "soundState": "number",
    "vibrateState": "number",
    "musicState": "number",
    "level": "number",
    "levelTubeSaveInfo": "object",
    "useTubeSkinId": "number",
    "useBallSkinId": "number",
    "useBgId": "number",
    "tempTubeHasBallNum": "number",
    "pauseUseNum": "number",
    "addTubeUseNum": "number",
    "addTime": "number",
    "jumpLevelNum": "number",
    "pack": "object",
    "coinNum": "number",
    "starNum": "number",
    "currentChallengeLevel": "number",
    "challengeLevelInfo": "object",
    "isFristGame": "number",
    "gameTime": "number",
    "levelTubeWenHaoSaveInfo": "object",
    "isGetCollectReward": "number",
    "isGetZhuoMianReward": "number",
    "resultShareTimeStamp": "number",
    "isFristSignIn": "number",
    "signInData": "object",
    "signInTime": "number",
    "topSignInDay": "number",
    "fightTipSignIn": "number",
    "mainTipSignIn": "number",
    "tipSignInTimeStamp": "number",
    "repairDataVersion": "number",
    "competitionScore": "number",
    "competitionDan": "number",
    "competitionTopDan": "number",
    "competitionTime": "number",
    "competitionNikeName": "array",
    "competitionReward": "object"
  },
  {
    "locaInfo": "locaInfo",
    "version": "1",
    "localVersion": "1",
    "userId": "1",
    "soundState": "1",
    "vibrateState": "1",
    "musicState": "1",
    "level": "1",
    "levelTubeSaveInfo": "{\"tubes\":[]}",
    "useTubeSkinId": "1001001",
    "useBallSkinId": "2001001",
    "useBgId": "3001001",
    "tempTubeHasBallNum": "0",
    "pauseUseNum": "0",
    "addTubeUseNum": "0",
    "addTime": "0",
    "jumpLevelNum": "0",
    "pack": "{\"1001001\":{\"state\":1},\"2001001\":{\"state\":1},\"3001001\":{\"state\":1}}",
    "coinNum": "0",
    "starNum": "0",
    "currentChallengeLevel": "1",
    "challengeLevelInfo": "{\"1\":{\"tubes\":[],\"state\":0,\"videoNum\":0}}",
    "isFristGame": "1",
    "gameTime": "-1",
    "levelTubeWenHaoSaveInfo": "{\"tubes\":[]}",
    "isGetCollectReward": "0",
    "isGetZhuoMianReward": "0",
    "resultShareTimeStamp": "0",
    "isFristSignIn": "1",
    "signInData": "{\"1\":{\"state\":0}}",
    "signInTime": "0",
    "topSignInDay": "0",
    "fightTipSignIn": "0",
    "mainTipSignIn": "0",
    "tipSignInTimeStamp": "0",
    "repairDataVersion": "0",
    "competitionScore": "0",
    "competitionDan": "1",
    "competitionTopDan": "1",
    "competitionTime": "0",
    "competitionNikeName": "[]",
    "competitionReward": "{\"1\":{\"state\":0}}"
  }
]